clatter/__init__.py
clatter/core.py
clatter/validators.py
clatter-0.1.1.dist-info/DESCRIPTION.rst
clatter-0.1.1.dist-info/METADATA
clatter-0.1.1.dist-info/RECORD
clatter-0.1.1.dist-info/WHEEL
clatter-0.1.1.dist-info/metadata.json
clatter-0.1.1.dist-info/top_level.txt
