Metadata-Version: 2.0
Name: clatter
Version: 0.1.1
Summary: A Doctest-stype Command Line Application Tester
Home-page: https://github.com/delgadom/clatter
Author: Michael Delgado
Author-email: UNKNOWN
License: MIT license
Keywords: clatter
Platform: UNKNOWN
Classifier: Development Status :: 2 - Pre-Alpha
Classifier: Intended Audience :: Developers
Classifier: License :: OSI Approved :: MIT License
Classifier: Natural Language :: English
Classifier: Programming Language :: Python :: 2
Classifier: Programming Language :: Python :: 2.7
Classifier: Programming Language :: Python :: 3
Classifier: Programming Language :: Python :: 3.3
Classifier: Programming Language :: Python :: 3.4
Classifier: Programming Language :: Python :: 3.5
Classifier: Programming Language :: Python :: 3.6
Requires-Dist: click (>=6.0)
Provides-Extra: test
Requires-Dist: Sphinx (>=1.4.1); extra == 'test'
Requires-Dist: click (>=6.0); extra == 'test'
Requires-Dist: coverage (>=4.0); extra == 'test'
Requires-Dist: flake8 (>=2.0); extra == 'test'
Requires-Dist: jinja2 (>=2.8); extra == 'test'
Requires-Dist: pip (>=8.0); extra == 'test'
Requires-Dist: pytest (>=3.0); extra == 'test'
Requires-Dist: pytest-cov (>=2.0); extra == 'test'
Requires-Dist: pytest-runner (>=2.5); extra == 'test'
Requires-Dist: sphinx-rtd-theme (>=0.1.0); extra == 'test'
Requires-Dist: tox (>=2.3.0); extra == 'test'
Requires-Dist: wheel (>=0.27); extra == 'test'
